msrc/appconfig_decl/decl_dataclasses.py
msrc_appconfig_dataclasses-0.5.8.dist-info/METADATA
msrc_appconfig_dataclasses-0.5.8.dist-info/WHEEL
msrc_appconfig_dataclasses-0.5.8.dist-info/top_level.txt
msrc_appconfig_dataclasses-0.5.8.dist-info/RECORD
